{
  "api": {
    "rickshareah": {
      "dependsOn": [
        {
          "attributes": [
            "UserPoolId"
          ],
          "category": "auth",
          "resourceName": "rickshareahea33e0e6"
        }
      ],
      "output": {
        "authConfig": {
          "additionalAuthenticationProviders": [
            {
              "authenticationType": "AMAZON_COGNITO_USER_POOLS",
              "userPoolConfig": {
                "userPoolId": "authrickshareahea33e0e6"
              }
            }
          ],
          "defaultAuthentication": {
            "apiKeyConfig": {
              "apiKeyExpirationDays": 7
            },
            "authenticationType": "API_KEY"
          }
        }
      },
      "providerPlugin": "awscloudformation",
      "service": "AppSync"
    }
  },
  "auth": {
    "rickshareahea33e0e6": {
      "customAuth": false,
      "dependsOn": [],
      "frontendAuthConfig": {
        "mfaConfiguration": "OFF",
        "mfaTypes": [
          "SMS"
        ],
        "passwordProtectionSettings": {
          "passwordPolicyCharacters": [],
          "passwordPolicyMinLength": 8
        },
        "signupAttributes": [
          "EMAIL"
        ],
        "socialProviders": [],
        "usernameAttributes": [
          "EMAIL"
        ],
        "verificationMechanisms": [
          "EMAIL"
        ]
      },
      "providerPlugin": "awscloudformation",
      "service": "Cognito"
    }
  },
  "function": {
    "processReceipt": {
      "build": true,
      "dependsOn": [
        {
          "attributes": [
            "BucketName"
          ],
          "category": "storage",
          "resourceName": "receipts"
        }
      ],
      "providerPlugin": "awscloudformation",
      "service": "Lambda"
    }
  },
  "hosting": {
    "amplifyhosting": {
      "lastPushTimeStamp": "2025-12-11T17:42:09.900Z",
      "service": "amplifyhosting",
      "type": "cicd"
    }
  },
  "storage": {
    "receipts": {
      "dependsOn": [],
      "providerPlugin": "awscloudformation",
      "service": "S3"
    }
  }
}